scrapy_llm_loader/__init__.py
scrapy_llm_loader/langchain_api.py
scrapy_llm_loader/langchain_integration.py
scrapy_llm_loader/loader.py
scrapy_llm_loader/output_parser.py
scrapy_llm_loader/prompt.py
scrapy_llm_loader/utils.py
scrapy_llm_loader-0.3.dist-info/METADATA
scrapy_llm_loader-0.3.dist-info/WHEEL
scrapy_llm_loader-0.3.dist-info/top_level.txt
scrapy_llm_loader-0.3.dist-info/RECORD
