Metadata-Version: 2.1
Name: scrapy-llm-loader
Version: 0.3
Summary: A Scrapy extension for data extraction using LangChain
